evolutionary_programming/__init__ .pxd
evolutionary_programming/__init__.py
evolutionary_programming/data_processing/__init__.py
evolutionary_programming/data_processing/data_utils.cpython-311-x86_64-linux-gnu.so
evolutionary_programming/data_processing/data_utils.pxd
evolutionary_programming/data_processing/data_utils.pyx
evolutionary_programming/data_processing/dataset.cpython-311-x86_64-linux-gnu.so
evolutionary_programming/data_processing/dataset.pxd
evolutionary_programming/data_processing/dataset.pyx
evolutionary_programming/data_processing/scalers.cpython-311-x86_64-linux-gnu.so
evolutionary_programming/data_processing/scalers.pxd
evolutionary_programming/data_processing/scalers.pyx
evolutionary_programming/neural_network/__init__.py
evolutionary_programming/neural_network/activation_functions.cpython-311-x86_64-linux-gnu.so
evolutionary_programming/neural_network/activation_functions.pxd
evolutionary_programming/neural_network/activation_functions.pyx
evolutionary_programming/neural_network/coding.cpython-311-x86_64-linux-gnu.so
evolutionary_programming/neural_network/coding.pxd
evolutionary_programming/neural_network/coding.pyx
evolutionary_programming/neural_network/ensemble.cpython-311-x86_64-linux-gnu.so
evolutionary_programming/neural_network/ensemble.pxd
evolutionary_programming/neural_network/ensemble.pyx
evolutionary_programming/neural_network/loss_functions.cpython-311-x86_64-linux-gnu.so
evolutionary_programming/neural_network/loss_functions.pxd
evolutionary_programming/neural_network/loss_functions.pyx
evolutionary_programming/neural_network/network.cpython-311-x86_64-linux-gnu.so
evolutionary_programming/neural_network/network.pxd
evolutionary_programming/neural_network/network.pyx
evolutionary_programming/neural_network/regularization.cpython-311-x86_64-linux-gnu.so
evolutionary_programming/neural_network/regularization.pxd
evolutionary_programming/neural_network/regularization.pyx
evolutionary_programming-0.8.1.dist-info/METADATA
evolutionary_programming-0.8.1.dist-info/WHEEL
evolutionary_programming-0.8.1.dist-info/RECORD
