Metadata-Version: 2.1
Name: evolutionary-programming
Version: 0.8.1
Summary: 
Author: Gabriel Soares Baptista
Author-email: gsoaresbaptista@gmail.com
Requires-Python: >=3.10,<3.12
Classifier: Programming Language :: Python :: 3
Classifier: Programming Language :: Python :: 3.10
Classifier: Programming Language :: Python :: 3.11
Requires-Dist: numpy (>=1.26.1,<2.0.0)
Requires-Dist: requests (>=2.31.0,<3.0.0)
